mletahmin/__init__.py
mletahmin/__main__.py
mletahmin/gamma.py
mletahmin/lomax.py
mletahmin/mle.py
mletahmin/pareto.py
mle_tahmin-0.1.6.dist-info/METADATA
mle_tahmin-0.1.6.dist-info/WHEEL
mle_tahmin-0.1.6.dist-info/top_level.txt
mle_tahmin-0.1.6.dist-info/RECORD
