Metadata-Version: 2.4
Name: MLE-Tahmin
Version: 0.1.6
Summary: Aktüerya için MLE parametre tahmin aracı (gamma, pareto, lomax)
Author: Melih Karagülmez
Requires-Python: >=3.9
Requires-Dist: numpy
Requires-Dist: scipy
Requires-Dist: pandas
